brokrest/__init__.py
brokrest-0.0.0.dist-info/LICENSE.md
brokrest-0.0.0.dist-info/METADATA
brokrest-0.0.0.dist-info/WHEEL
brokrest-0.0.0.dist-info/RECORD
