Metadata-Version: 2.3
Name: brokrest
Version: 0.0.0
Summary: Brokers can rest now.
License: GPL
Author: RenChu Wang
Author-email: patrick1031wang@gmail.com
Requires-Python: >=3.12,<4.0
Classifier: License :: Other/Proprietary License
Classifier: Programming Language :: Python :: 3
Classifier: Programming Language :: Python :: 3.12
Classifier: Programming Language :: Python :: 3.13
Requires-Dist: freqtrade (>=2025.3,<2026.0)
Requires-Dist: numpy
Requires-Dist: pandas (>=2.2.3,<3.0.0)
Requires-Dist: scipy (>=1.15.2,<2.0.0)
Requires-Dist: sympy (>=1.12.0)
Requires-Dist: torch (>=2.6.0,<3.0.0)
